llm/__init__.py
llm/admin.py
llm/apps.py
llm/forms.py
llm/tests.py
llm/urls.py
llm/views.py
llm/migrations/0001_initial.py
llm/migrations/0002_rename_modelapi_modelproviderapi_and_more.py
llm/migrations/0003_openaichatquery.py
llm/migrations/0004_prompt_num_input_vars.py
llm/migrations/0005_remove_openaichatquery_query_response_and_more.py
llm/migrations/0006_remove_prompt_input_variables_and_more.py
llm/migrations/0007_alter_modelproviderapi_id_alter_openaichatquery_id_and_more.py
llm/migrations/__init__.py
llm/models/__init__.py
llm/models/base.py
llm/models/prompts.py
llm/models/queries.py
django_llm-0.1.3.dist-info/AUTHORS
django_llm-0.1.3.dist-info/LICENSE.md
django_llm-0.1.3.dist-info/METADATA
django_llm-0.1.3.dist-info/WHEEL
django_llm-0.1.3.dist-info/top_level.txt
django_llm-0.1.3.dist-info/RECORD
