Metadata-Version: 2.1
Name: django-llm
Version: 0.1.3
Summary: A LLM (Large Language Model) app for Django
Home-page: https://github.com/mikrl/django-llm
Author: Michael Lynch
Author-email: michael@flatlander.dev
License: MIT
Classifier: Development Status :: 2 - Pre-Alpha
Classifier: Environment :: Web Environment
Classifier: Framework :: Django
Classifier: Framework :: Django :: 4
Classifier: Framework :: Django :: 4.1
Classifier: Intended Audience :: Developers
Classifier: Intended Audience :: Information Technology
Classifier: Intended Audience :: Science/Research
Classifier: Operating System :: OS Independent
Classifier: Programming Language :: Python :: 3 :: Only
Classifier: Programming Language :: Python :: 3
Classifier: Programming Language :: Python :: 3.11
Classifier: License :: OSI Approved :: MIT License
Classifier: Topic :: Scientific/Engineering
Classifier: Topic :: Scientific/Engineering :: Artificial Intelligence
Classifier: Topic :: Scientific/Engineering :: Human Machine Interfaces
Classifier: Topic :: Software Development :: User Interfaces
Requires-Python: >=3.11
License-File: LICENSE.md
License-File: AUTHORS
Requires-Dist: Django (==4.1.7)
Requires-Dist: openai (==0.27.2)
Requires-Dist: langchain (==0.0.121)
Requires-Dist: llama-index (==0.4.36)
Requires-Dist: pytest (==7.2.2)
